mail_library/__init__.py
mail_library/mail.py
mail_library/main.py
mail_library-0.1.0.dist-info/METADATA
mail_library-0.1.0.dist-info/WHEEL
mail_library-0.1.0.dist-info/RECORD
