Metadata-Version: 2.1
Name: mail-library
Version: 0.1.0
Summary: 
Author: miguelnunez15
Author-email: 124568587+miguelnunez15@users.noreply.github.com
Requires-Python: >=3.11,<4.0
Classifier: Programming Language :: Python :: 3
Classifier: Programming Language :: Python :: 3.11
Classifier: Programming Language :: Python :: 3.12
Classifier: Programming Language :: Python :: 3.13
